passagemath_symbolics-10.6.43.dist-info/RECORD
passagemath_symbolics-10.6.43.dist-info/WHEEL
passagemath_symbolics-10.6.43.dist-info/top_level.txt
passagemath_symbolics-10.6.43.dist-info/METADATA
passagemath_symbolics/__init__.py
passagemath_symbolics/.dylibs/libgmp.10.dylib
sage/all__sagemath_symbolics.py
sage/dynamics/all__sagemath_symbolics.py
sage/dynamics/complex_dynamics/mandel_julia_helper.pyx
sage/dynamics/complex_dynamics/mandel_julia.py
sage/dynamics/complex_dynamics/all.py
sage/dynamics/complex_dynamics/mandel_julia_helper.cpython-312-darwin.so
sage/manifolds/catalog.py
sage/manifolds/section_module.py
sage/manifolds/vector_bundle_fiber_element.py
sage/manifolds/topological_submanifold.py
sage/manifolds/manifold.py
sage/manifolds/calculus_method.py
sage/manifolds/vector_bundle.py
sage/manifolds/scalarfield.py
sage/manifolds/chart.py
sage/manifolds/all.py
sage/manifolds/section.py
sage/manifolds/vector_bundle_fiber.py
sage/manifolds/point.py
sage/manifolds/subset.py
sage/manifolds/continuous_map_image.py
sage/manifolds/chart_func.py
sage/manifolds/manifold_homset.py
sage/manifolds/structure.py
sage/manifolds/family.py
sage/manifolds/trivialization.py
sage/manifolds/continuous_map.py
sage/manifolds/local_frame.py
sage/manifolds/utilities.py
sage/manifolds/operators.py
sage/manifolds/scalarfield_algebra.py
sage/manifolds/differentiable/diff_map.py
sage/manifolds/differentiable/vectorfield_module.py
sage/manifolds/differentiable/tensorfield_module.py
sage/manifolds/differentiable/mixed_form_algebra.py
sage/manifolds/differentiable/symplectic_form_test.py
sage/manifolds/differentiable/manifold.py
sage/manifolds/differentiable/vector_bundle.py
sage/manifolds/differentiable/tangent_space.py
sage/manifolds/differentiable/affine_connection.py
sage/manifolds/differentiable/pseudo_riemannian.py
sage/manifolds/differentiable/differentiable_submanifold.py
sage/manifolds/differentiable/tensorfield_paral.py
sage/manifolds/differentiable/scalarfield.py
sage/manifolds/differentiable/vectorfield.py
sage/manifolds/differentiable/chart.py
sage/manifolds/differentiable/multivectorfield.py
